calypso_anemometer/__init__.py
calypso_anemometer/cli.py
calypso_anemometer/core.py
calypso_anemometer/engine.py
calypso_anemometer/exception.py
calypso_anemometer/fake.py
calypso_anemometer/model.py
calypso_anemometer/util.py
calypso_anemometer/telemetry/__init__.py
calypso_anemometer/telemetry/adapter.py
calypso_anemometer/telemetry/model.py
calypso_anemometer/telemetry/network.py
calypso_anemometer/telemetry/nmea0183.py
calypso_anemometer/telemetry/signalk.py
doc/backlog.rst
doc/preflight.rst
doc/production.rst
doc/sandbox.rst
doc/troubleshooting.rst
examples/calypso_read.py
examples/calypso_subscribe.py
examples/calypso_telemetry_nmea0183.py
examples/calypso_telemetry_signalk.py
testing/__init__.py
testing/conftest.py
testing/data.py
testing/test_cli.py
testing/test_core_connect.py
testing/test_core_discovery.py
testing/test_core_info_status.py
testing/test_core_misc.py
testing/test_core_reading.py
testing/test_core_write.py
testing/test_engine.py
testing/test_examples.py
testing/test_fake.py
testing/test_model.py
testing/test_telemetry.py
testing/test_util.py
calypso_anemometer-0.6.0.dist-info/LICENSE
calypso_anemometer-0.6.0.dist-info/METADATA
calypso_anemometer-0.6.0.dist-info/WHEEL
calypso_anemometer-0.6.0.dist-info/entry_points.txt
calypso_anemometer-0.6.0.dist-info/top_level.txt
calypso_anemometer-0.6.0.dist-info/RECORD
