Metadata-Version: 2.1
Name: calypso-anemometer
Version: 0.6.0
Summary: Python driver for the Calypso UP10 anemometer
Author: Holger Marseille
Author-email: Andreas Motl <andreas.motl@panodata.org>
License: AGPL-3.0, EUPL-1.2
Project-URL: changelog, https://github.com/maritime-labs/calypso-anemometer/blob/main/CHANGES.rst
Project-URL: documentation, https://github.com/maritime-labs/calypso-anemometer
Project-URL: homepage, https://github.com/maritime-labs/calypso-anemometer
Project-URL: repository, https://github.com/maritime-labs/calypso-anemometer
Keywords: anemometer,ble,bluetooth,bluetooth-le,bluetooth-low-energy,calypso,environmental-monitoring,nmea,nmea-0183,opencpn,openplotter,signalk,signalk-plugin,solar,ultrasonic,ultrasonic-anemometry,ultrasonic-sensor,up10,wind-meter
Classifier: Development Status :: 4 - Beta
Classifier: Environment :: Console
Classifier: Intended Audience :: Customer Service
Classifier: Intended Audience :: Developers
Classifier: Intended Audience :: Education
Classifier: Intended Audience :: Information Technology
Classifier: Intended Audience :: Manufacturing
Classifier: Intended Audience :: Science/Research
Classifier: Intended Audience :: System Administrators
Classifier: Intended Audience :: Telecommunications Industry
Classifier: License :: OSI Approved :: GNU Affero General Public License v3
Classifier: License :: OSI Approved :: European Union Public Licence 1.2 (EUPL 1.2)
Classifier: Operating System :: MacOS :: MacOS X
Classifier: Operating System :: POSIX :: Linux
Classifier: Operating System :: Unix
Classifier: Programming Language :: Python
Classifier: Programming Language :: Python :: 3.7
Classifier: Programming Language :: Python :: 3.8
Classifier: Programming Language :: Python :: 3.9
Classifier: Programming Language :: Python :: 3.10
Classifier: Programming Language :: Python :: 3.11
Classifier: Topic :: Communications
Classifier: Topic :: Education
Classifier: Topic :: Home Automation
Classifier: Topic :: Scientific/Engineering
Classifier: Topic :: Software Development :: Libraries
Classifier: Topic :: Software Development :: Quality Assurance
Classifier: Topic :: Software Development :: Object Brokering
Classifier: Topic :: System :: Emulators
Classifier: Topic :: System :: Hardware
Classifier: Topic :: System :: Logging
Classifier: Topic :: System :: Monitoring
Classifier: Topic :: System :: Networking
Classifier: Topic :: System :: Networking :: Monitoring
Classifier: Topic :: System :: Systems Administration
Classifier: Topic :: Utilities
Requires-Python: >=3.7
License-File: LICENSE
Requires-Dist: bleak (<1)
Requires-Dist: click (<9)
Provides-Extra: develop
Requires-Dist: black (<24) ; extra == 'develop'
Requires-Dist: isort (<6) ; extra == 'develop'
Requires-Dist: poethepoet (<0.19) ; extra == 'develop'
Requires-Dist: proselint (==0.13) ; extra == 'develop'
Requires-Dist: pyproject-fmt (<0.10) ; extra == 'develop'
Requires-Dist: ruff (==0.0.252) ; extra == 'develop'
Requires-Dist: validate-pyproject (<0.13) ; extra == 'develop'
Provides-Extra: fake
Requires-Dist: aiorate (<2,>1) ; (python_version >= "3.7") and extra == 'fake'
Provides-Extra: release
Requires-Dist: build (<1) ; extra == 'release'
Requires-Dist: twine (<5) ; extra == 'release'
Requires-Dist: minibump (<1) ; (python_version >= "3.10") and extra == 'release'
Provides-Extra: test
Requires-Dist: pytest (<8) ; extra == 'test'
Requires-Dist: pytest-asyncio (<1) ; extra == 'test'
Requires-Dist: pytest-cov (<4) ; extra == 'test'
Requires-Dist: pytest-mock (<4) ; extra == 'test'
